{
  "$schema": "https://mintlify.com/schema.json",
  "name": "Midland",
  "logo": {
    "dark": "/logo/midland-logo.png",
    "light": "/logo/midland-logo.png"
  },
  "favicon": "/favicon.png",
  "colors": {
    "primary": "#9563FF",
    "light": "#AE87FF",
    "dark": "#0D001D",
    "background": {
      "dark": "#090014"
    },
    "anchors": {
      "from": "#FF7F57",
      "to": "#9563FF"
    }
  },
  "api": {
    "auth": {
      "method": "bearer"
    }
  },
  "topbarLinks": [
    {
      "name": "Support",
      "url": "mailto:support@midland.io"
    }
  ],
  "tabs": [
    {
      "name": "API Reference",
      "url": "api-reference"
    }
  ],
  "anchors": [],
  "navigation": [
    {
      "group": "Get Started",
      "pages": ["introduction", "quickstart", "development"]
    },
    {
      "group": "Essentials",
      "pages": [
        "essentials/markdown",
        "essentials/code",
        "essentials/images",
        "essentials/settings",
        "essentials/navigation"
      ]
    },
    {
      "group": "Auth",
      "pages": [
        "api-reference/auth/login"
      ]
    },
    {
      "group": "Tenancies",
      "pages": [
        "api-reference/tenancies/tenancies"
      ]
    },
    {
      "group": "Providers",
      "pages": [
        "api-reference/providers/providers"
      ]
    },
    {
      "group": "Connections",
      "pages": [
        "api-reference/connections/connections",
        "api-reference/connections/connection-by-id"
      ]
    },
    {
      "group": "Devices",
      "pages": [
        "api-reference/devices/devices",
        "api-reference/devices/device-by-id"
      ]
    },
    {
      "group": "Events",
      "pages": [
        "api-reference/events/events",
        "api-reference/events/event-by-id"
      ]
    },
    {
      "group": "Trips",
      "pages": [
        "api-reference/trips/trips",
        "api-reference/trips/trip-by-id"
      ]
    },
    {
      "group": "Positions",
      "pages": [
        "api-reference/positions/positions"
      ]
    }
  ],
  "openapi": ["/openapi.json"]
}
